first_trial/__init__.py
first_trial-0.0.1.dist-info/LICENSE
first_trial-0.0.1.dist-info/METADATA
first_trial-0.0.1.dist-info/WHEEL
first_trial-0.0.1.dist-info/top_level.txt
first_trial-0.0.1.dist-info/RECORD
