Metadata-Version: 2.1
Name: first_trial
Version: 0.0.1
Summary: First Trial
Home-page: https://github.com/etn-electrical/first_trial
Author: Supriya Pasarkar
Author-email: pasarkarsk1998@gmail.com
Project-URL: Bug Tracker, https://github.com/etn-electrical/first_trial/issues
Classifier: Programming Language :: Python :: 3
Classifier: License :: OSI Approved :: MIT License
Classifier: Operating System :: OS Independent
Requires-Python: >=3.8
License-File: LICENSE
